<?xml version="1.0" encoding="UTF-8"?><entries>
<entry field="0 field"/>
<entry field="4 field"/>
<entry field="8 field"/>
<entry field="12 field"/>
<entry field="16 field"/>
<entry field="20 field"/>
<entry field="24 field"/>
<entry field="28 field"/>
<entry field="32 field"/>
<entry field="36 field"/>
<entry field="40 field"/>
<entry field="44 field"/>
<entry field="48 field"/>
<entry field="52 field"/>
<entry field="56 field"/>
<entry field="60 field"/>
<entry field="64 field"/>
<entry field="68 field"/>
<entry field="72 field"/>
<entry field="76 field"/>
<entry field="80 field"/>
<entry field="84 field"/>
<entry field="88 field"/>
<entry field="92 field"/>
<entry field="96 field"/>
<entry field="1 field"/>
<entry field="5 field"/>
<entry field="9 field"/>
<entry field="13 field"/>
<entry field="17 field"/>
<entry field="21 field"/>
<entry field="25 field"/>
<entry field="29 field"/>
<entry field="33 field"/>
<entry field="37 field"/>
<entry field="41 field"/>
<entry field="45 field"/>
<entry field="49 field"/>
<entry field="53 field"/>
<entry field="57 field"/>
<entry field="61 field"/>
<entry field="65 field"/>
<entry field="69 field"/>
<entry field="73 field"/>
<entry field="77 field"/>
<entry field="81 field"/>
<entry field="85 field"/>
<entry field="89 field"/>
<entry field="93 field"/>
<entry field="97 field"/>
<entry field="2 field"/>
<entry field="6 field"/>
<entry field="10 field"/>
<entry field="14 field"/>
<entry field="18 field"/>
<entry field="22 field"/>
<entry field="26 field"/>
<entry field="30 field"/>
<entry field="34 field"/>
<entry field="38 field"/>
<entry field="42 field"/>
<entry field="46 field"/>
<entry field="50 field"/>
<entry field="54 field"/>
<entry field="58 field"/>
<entry field="62 field"/>
<entry field="66 field"/>
<entry field="70 field"/>
<entry field="74 field"/>
<entry field="78 field"/>
<entry field="82 field"/>
<entry field="86 field"/>
<entry field="90 field"/>
<entry field="94 field"/>
<entry field="98 field"/>
<entry field="3 field"/>
<entry field="7 field"/>
<entry field="11 field"/>
<entry field="15 field"/>
<entry field="19 field"/>
<entry field="23 field"/>
<entry field="27 field"/>
<entry field="31 field"/>
<entry field="35 field"/>
<entry field="39 field"/>
<entry field="43 field"/>
<entry field="47 field"/>
<entry field="51 field"/>
<entry field="55 field"/>
<entry field="59 field"/>
<entry field="63 field"/>
<entry field="67 field"/>
<entry field="71 field"/>
<entry field="75 field"/>
<entry field="79 field"/>
<entry field="83 field"/>
<entry field="87 field"/>
<entry field="91 field"/>
<entry field="95 field"/>
<entry field="99 field"/>
</entries>
